{
	"name": "Bijou",
	"img": [
		"Bijou.jpg"
	],
	"lists": [],
	"serve": "Straight up",
	"garnish": "",
	"drinkware": "Cocktail glass",
	"ingredients": [
		{
			"name": "Gin",
			"measure": "1",
			"unit": "part"
		},
		{
			"name": "Green Chartreuse",
			"measure": "1",
			"unit": "part"
		},
		{
			"name": "Sweet Vermouth",
			"measure": "1",
			"unit": "part"
		},
		{
			"name": "Orange Bitters",
			"measure": "1",
			"unit": "dash"
		}
	],
	"method": "Stir in mixing glass with ice and strain"
}
